py_uboot_env/__init__.py
py_uboot_env/cli.py
py_uboot_env/uboot_env.py
py_uboot_env/examples/advanced_usage.py
py_uboot_env/examples/basic_usage.py
py_uboot_env/examples/modify_and_revert.py
py_uboot_env-1.0.0.dist-info/licenses/LICENSE
py_uboot_env-1.0.0.dist-info/METADATA
py_uboot_env-1.0.0.dist-info/WHEEL
py_uboot_env-1.0.0.dist-info/entry_points.txt
py_uboot_env-1.0.0.dist-info/top_level.txt
py_uboot_env-1.0.0.dist-info/RECORD
