Metadata-Version: 2.4
Name: py-uboot-env
Version: 1.0.0
Summary: A package for reading, modifying, and writing U-Boot environment files
Author-email: Edel Macias <author@example.com>
License-Expression: Unlicense
Project-URL: Homepage, https://github.com/cubix-mx/py-uboot-env
Project-URL: Bug Tracker, https://github.com/cubix-mx/py-uboot-env/issues
Classifier: Programming Language :: Python :: 3
Classifier: Operating System :: OS Independent
Requires-Python: >=3.6
License-File: LICENSE
Dynamic: license-file
